schnell/__init__.py
schnell/correlation.py
schnell/detector.py
schnell/mapping.py
schnell-0.2.0.dist-info/LICENSE
schnell-0.2.0.dist-info/METADATA
schnell-0.2.0.dist-info/WHEEL
schnell-0.2.0.dist-info/top_level.txt
schnell-0.2.0.dist-info/RECORD
