Metadata-Version: 2.1
Name: schnell
Version: 0.2.0
Summary: schNell - Fast calculation of N_l for GW anisotropies
Home-page: https://github.com/damonge/schNell
Author: David Alonso
Author-email: david.alonso@physics.ox.ac.uk
License: UNKNOWN
Platform: UNKNOWN
Requires-Dist: numpy
Requires-Dist: scipy
Requires-Dist: healpy
